tea_sdk/__init__.py
tea_sdk/cli.py
tea_sdk/tea_sdk.py
tea_sdk-0.1.0.dist-info/AUTHORS.rst
tea_sdk-0.1.0.dist-info/LICENSE
tea_sdk-0.1.0.dist-info/METADATA
tea_sdk-0.1.0.dist-info/WHEEL
tea_sdk-0.1.0.dist-info/entry_points.txt
tea_sdk-0.1.0.dist-info/top_level.txt
tea_sdk-0.1.0.dist-info/RECORD
